src/__init__.py
src/yoyo.py
src/core/InstallOptions.py
src/core/Module.py
src/core/Plugins.py
src/core/Steps.py
src/core/Store.py
src/core/Yoyo.py
src/core/__init__.py
src/core/log.py
src/modules/__init__.py
src/modules/blih.py
src/modules/cmake.py
src/modules/debian.py
src/modules/git.py
src/modules/google-chrome.py
src/modules/i3-gaps.py
src/modules/i3.py
src/modules/jbtoolbox.py
src/modules/tree.py
src/plugins/__init__.py
src/plugins/plugin_git_update.py
src/stores/Local.py
src/stores/YLocal.py
src/stores/__init__.py
yoyopkg-2.5.dist-info/METADATA
yoyopkg-2.5.dist-info/WHEEL
yoyopkg-2.5.dist-info/entry_points.txt
yoyopkg-2.5.dist-info/top_level.txt
yoyopkg-2.5.dist-info/RECORD
