Metadata-Version: 2.1
Name: yoyopkg
Version: 2.5
Summary: A modular package manager
Home-page: https://github.com/ethanquix/yoyo
Author: dwyzlic
Author-email: dimitriwyzlic@gmail.com
License: MIT
Platform: UNKNOWN
Requires-Dist: colorama
Requires-Dist: requests
